edge_mdt_cl_dev-1.1.0.dev2.dist-info/licenses/LICENSE.md
edgemdt_cl/__init__.py
edgemdt_cl/version.py
edgemdt_cl/common/__init__.py
edgemdt_cl/common/box_util.py
edgemdt_cl/keras/__init__.py
edgemdt_cl/keras/base_custom_layer.py
edgemdt_cl/keras/custom_objects.py
edgemdt_cl/keras/object_detection/__init__.py
edgemdt_cl/keras/object_detection/faster_rcnn_box_decode.py
edgemdt_cl/keras/object_detection/score_converter.py
edgemdt_cl/keras/object_detection/ssd_post_process.py
edgemdt_cl/pytorch/__init__.py
edgemdt_cl/pytorch/custom_layer.py
edgemdt_cl/pytorch/custom_lib.py
edgemdt_cl/pytorch/box_decode/__init__.py
edgemdt_cl/pytorch/box_decode/box_decode.py
edgemdt_cl/pytorch/box_decode/box_decode_onnx.py
edgemdt_cl/pytorch/box_decode/box_decode_ort.py
edgemdt_cl/pytorch/nms/__init__.py
edgemdt_cl/pytorch/nms/nms.py
edgemdt_cl/pytorch/nms/nms_common.py
edgemdt_cl/pytorch/nms/nms_onnx.py
edgemdt_cl/pytorch/nms/nms_ort.py
edgemdt_cl/pytorch/nms/nms_with_indices.py
edgemdt_cl/pytorch/nms_obb/__init__.py
edgemdt_cl/pytorch/nms_obb/nms_obb.py
edgemdt_cl/pytorch/nms_obb/nms_obb_common.py
edgemdt_cl/pytorch/nms_obb/nms_obb_onnx.py
edgemdt_cl/pytorch/nms_obb/nms_obb_ort.py
edgemdt_cl/util/__init__.py
edgemdt_cl/util/import_util.py
edgemdt_cl/util/test_util.py
edge_mdt_cl_dev-1.1.0.dev2.dist-info/METADATA
edge_mdt_cl_dev-1.1.0.dev2.dist-info/WHEEL
edge_mdt_cl_dev-1.1.0.dev2.dist-info/top_level.txt
edge_mdt_cl_dev-1.1.0.dev2.dist-info/RECORD
