Metadata-Version: 2.4
Name: edge-mdt-cl-dev
Version: 1.1.0.dev2
Summary: Edge MDT Custom Layers package
Classifier: Programming Language :: Python :: 3
Classifier: License :: OSI Approved :: Apache Software License
Classifier: Operating System :: OS Independent
Classifier: Topic :: Scientific/Engineering :: Artificial Intelligence
License-File: LICENSE.md
Requires-Dist: numpy
Requires-Dist: packaging
Provides-Extra: torch
Requires-Dist: torch==2.5.*; extra == "torch"
Requires-Dist: torchvision==0.20.*; extra == "torch"
Requires-Dist: onnx==1.17.*; extra == "torch"
Requires-Dist: onnxruntime==1.21.*; extra == "torch"
Requires-Dist: onnxruntime_extensions==0.13.*; extra == "torch"
Provides-Extra: tf
Requires-Dist: tensorflow==2.15.*; extra == "tf"
Dynamic: license-file
Dynamic: provides-extra
